README
setup.py
spacestatus.py
spacestatus_export.egg-info/PKG-INFO
spacestatus_export.egg-info/SOURCES.txt
spacestatus_export.egg-info/dependency_links.txt
spacestatus_export.egg-info/entry_points.txt
spacestatus_export.egg-info/pbr.json
spacestatus_export.egg-info/requires.txt
spacestatus_export.egg-info/top_level.txt