Metadata-Version: 1.1
Name: spacestatus-export
Version: 0.1
Summary: Get historical space API data
Home-page: http://dada.pink/spacestatus-export
Author: Thomas Levine
Author-email: _@thomaslevine.com
License: AGPL
Platform: UNKNOWN
Classifier: Programming Language :: Python :: 3.4
